abayestest/__init__.py
abayestest/_globals.py
abayestest/abayestest.py
abayestest/templates/__init__.py
abayestest/templates/base.stan
abayestest/templates/chunks/copyright.stan
abayestest/templates/distributions/__init__.py
abayestest/templates/distributions/bernoulli.stan
abayestest/templates/distributions/binomial.stan
abayestest/templates/distributions/gamma.stan
abayestest/templates/distributions/lognormal.stan
abayestest/templates/distributions/normal.stan
abayestest/templates/distributions/poisson.stan
abayestest-0.0.4.dist-info/LICENSE
abayestest-0.0.4.dist-info/METADATA
abayestest-0.0.4.dist-info/WHEEL
abayestest-0.0.4.dist-info/top_level.txt
abayestest-0.0.4.dist-info/RECORD
