Metadata-Version: 2.1
Name: abayestest
Version: 0.0.4
Requires-Python: >=3.10
License-File: LICENSE
Requires-Dist: appnope ==0.1.3
Requires-Dist: arviz ==0.16.1
Requires-Dist: asttokens ==2.2.1
Requires-Dist: backcall ==0.2.0
Requires-Dist: cmdstanpy ==1.1.0
Requires-Dist: contourpy ==1.1.0
Requires-Dist: cycler ==0.11.0
Requires-Dist: decorator ==5.1.1
Requires-Dist: exceptiongroup ==1.1.2
Requires-Dist: executing ==1.2.0
Requires-Dist: fonttools ==4.42.0
Requires-Dist: h5netcdf ==1.2.0
Requires-Dist: h5py ==3.9.0
Requires-Dist: iniconfig ==2.0.0
Requires-Dist: jedi ==0.19.0
Requires-Dist: Jinja2 ==3.1.2
Requires-Dist: kiwisolver ==1.4.4
Requires-Dist: MarkupSafe ==2.1.3
Requires-Dist: matplotlib ==3.7.2
Requires-Dist: matplotlib-inline ==0.1.6
Requires-Dist: numpy ==1.25.2
Requires-Dist: packaging ==23.1
Requires-Dist: pandas ==2.0.3
Requires-Dist: parso ==0.8.3
Requires-Dist: pexpect ==4.8.0
Requires-Dist: pickleshare ==0.7.5
Requires-Dist: Pillow ==10.0.0
Requires-Dist: pluggy ==1.2.0
Requires-Dist: prompt-toolkit ==3.0.39
Requires-Dist: ptyprocess ==0.7.0
Requires-Dist: pure-eval ==0.2.2
Requires-Dist: Pygments ==2.16.1
Requires-Dist: pyparsing ==3.0.9
Requires-Dist: python-dateutil ==2.8.2
Requires-Dist: pytz ==2023.3
Requires-Dist: scipy ==1.11.1
Requires-Dist: six ==1.16.0
Requires-Dist: stack-data ==0.6.2
Requires-Dist: tomli ==2.0.1
Requires-Dist: tqdm ==4.66.0
Requires-Dist: traitlets ==5.9.0
Requires-Dist: typing-extensions ==4.7.1
Requires-Dist: tzdata ==2023.3
Requires-Dist: wcwidth ==0.2.6
Requires-Dist: xarray ==2023.7.0
Requires-Dist: xarray-einstats ==0.6.0
